django_auth0/__init__.py
django_auth0/apps.py
django_auth0/auth_backend.py
django_auth0/auth_helpers.py
django_auth0/context_processors.py
django_auth0/models.py
django_auth0/urls.py
django_auth0/utils.py
django_auth0/views.py
django_auth0-0.0.3.dist-info/DESCRIPTION.rst
django_auth0-0.0.3.dist-info/METADATA
django_auth0-0.0.3.dist-info/RECORD
django_auth0-0.0.3.dist-info/WHEEL
django_auth0-0.0.3.dist-info/metadata.json
django_auth0-0.0.3.dist-info/top_level.txt
