Metadata-Version: 1.1
Name: django-auth0
Version: 0.0.3
Summary: Django Auth0 authentication background
Home-page: https://github.com/imanhodjaev/django-auth0
Author: Sultan Imanhodjaev
Author-email: sultan.imanhodjaev@gmail.com
License: MIT
Keywords: django-auth0 auth0
Platform: UNKNOWN
Classifier: Development Status :: 3 - Alpha
Classifier: Framework :: Django
Classifier: Framework :: Django :: 1.8
Classifier: Framework :: Django :: 1.9
Classifier: Intended Audience :: Developers
Classifier: License :: OSI Approved :: BSD License
Classifier: Natural Language :: English
Classifier: Programming Language :: Python :: 2.7
Classifier: Programming Language :: Python :: 3
Classifier: Programming Language :: Python :: 3.5
